streamlit_ollama_agent/__init__.py
streamlit_ollama_agent/agent.py
streamlit_ollama_agent/app.py
streamlit_ollama_agent-0.1.1.dist-info/LICENSE
streamlit_ollama_agent-0.1.1.dist-info/METADATA
streamlit_ollama_agent-0.1.1.dist-info/WHEEL
streamlit_ollama_agent-0.1.1.dist-info/top_level.txt
streamlit_ollama_agent-0.1.1.dist-info/RECORD
