Metadata-Version: 2.2
Name: streamlit-ollama-agent
Version: 0.1.1
Summary: A reusable Streamlit-based chat interface for Ollama models using PydanticAI
Home-page: https://github.com/yourusername/streamlit-ollama-agent
Author: Shenakiii
Author-email: re@dac.ted
Classifier: Development Status :: 3 - Alpha
Classifier: Intended Audience :: Developers
Classifier: License :: OSI Approved :: MIT License
Classifier: Programming Language :: Python :: 3
Classifier: Programming Language :: Python :: 3.8
Classifier: Programming Language :: Python :: 3.9
Classifier: Programming Language :: Python :: 3.10
Classifier: Programming Language :: Python :: 3.11
Requires-Python: >=3.8
License-File: LICENSE
Requires-Dist: streamlit>=1.24.0
Requires-Dist: openai>=1.0.0
Requires-Dist: pydantic-ai>=0.0.1
Requires-Dist: httpx>=0.24.0
Dynamic: author
Dynamic: author-email
Dynamic: classifier
Dynamic: description
Dynamic: description-content-type
Dynamic: home-page
Dynamic: requires-dist
Dynamic: requires-python
Dynamic: summary
